odoo8_addon_product_analytic-8.0.1.0.0.99.dev30-py3.8-nspkg.pth
odoo_addons/product_analytic/README.rst
odoo_addons/product_analytic/__init__.py
odoo_addons/product_analytic/__openerp__.py
odoo_addons/product_analytic/account_invoice.py
odoo_addons/product_analytic/product.py
odoo_addons/product_analytic/product_view.xml
odoo_addons/product_analytic/i18n/bs.po
odoo_addons/product_analytic/i18n/ca.po
odoo_addons/product_analytic/i18n/cs.po
odoo_addons/product_analytic/i18n/de.po
odoo_addons/product_analytic/i18n/es.po
odoo_addons/product_analytic/i18n/es_ES.po
odoo_addons/product_analytic/i18n/es_MX.po
odoo_addons/product_analytic/i18n/fi.po
odoo_addons/product_analytic/i18n/fr.po
odoo_addons/product_analytic/i18n/fr_CH.po
odoo_addons/product_analytic/i18n/hr.po
odoo_addons/product_analytic/i18n/hr_HR.po
odoo_addons/product_analytic/i18n/it.po
odoo_addons/product_analytic/i18n/nl.po
odoo_addons/product_analytic/i18n/nl_BE.po
odoo_addons/product_analytic/i18n/nl_NL.po
odoo_addons/product_analytic/i18n/product_analytic.pot
odoo_addons/product_analytic/i18n/pt_BR.po
odoo_addons/product_analytic/i18n/pt_PT.po
odoo_addons/product_analytic/i18n/ro.po
odoo_addons/product_analytic/i18n/sk.po
odoo_addons/product_analytic/i18n/sl.po
odoo_addons/product_analytic/i18n/tr.po
odoo_addons/product_analytic/i18n/tr_TR.po
odoo_addons/product_analytic/i18n/vi_VN.po
odoo_addons/product_analytic/i18n/zh_CN.po
odoo_addons/product_analytic/static/description/icon.png
odoo_addons/product_analytic/tests/__init__.py
odoo_addons/product_analytic/tests/test_account_invoice.py
odoo8_addon_product_analytic-8.0.1.0.0.99.dev30.dist-info/METADATA
odoo8_addon_product_analytic-8.0.1.0.0.99.dev30.dist-info/WHEEL
odoo8_addon_product_analytic-8.0.1.0.0.99.dev30.dist-info/namespace_packages.txt
odoo8_addon_product_analytic-8.0.1.0.0.99.dev30.dist-info/top_level.txt
odoo8_addon_product_analytic-8.0.1.0.0.99.dev30.dist-info/RECORD
