Metadata-Version: 2.1
Name: odoo8-addon-product-analytic
Version: 8.0.1.0.0.99.dev30
Summary: Add analytic account on products and product categories
Home-page: http://www.akretion.com
Author: Akretion, Antiun Ingeniería S.L., Odoo Community Association (OCA)
Author-email: support@odoo-community.org
License: AGPL-3
Platform: UNKNOWN
Classifier: Programming Language :: Python
Classifier: Framework :: Odoo
Classifier: Framework :: Odoo :: 8.0
Classifier: License :: OSI Approved :: GNU Affero General Public License v3
Requires-Python: ~=2.7
Requires-Dist: odoo (<9.0a,>=8.0a)
